protobuf_tools
