Metadata-Version: 1.1
Name: protobuf-tools
Version: 0.0.3
Summary: A library for adding some usability tools for working with protobuf
Home-page: https://github.com/ajbansal/protobuf-tools
Author: Abhijit Bansal
Author-email: pip@abhijitbansal.com
License: MIT
Platform: UNKNOWN
Classifier: Development Status :: 3 - Alpha
Classifier: License :: OSI Approved :: MIT License
Classifier: Programming Language :: Python :: 3.6
Classifier: Topic :: Software Development :: Code Generators
